crepex_pyutil/__init__.py
crepex_pyutil/collections.py
crepex_pyutil/dates.py
crepex_pyutil/exceptions.py
crepex_pyutil/math.py
crepex_pyutil/requests/__init__.py
crepex_pyutil/requests/helper.py
crepex_pyutil/requests/slack.py
crepex_pyutil/requests/types.py
crepex_pyutil/string.py
crepex_pyutil-0.18.0.dist-info/METADATA
crepex_pyutil-0.18.0.dist-info/WHEEL
crepex_pyutil-0.18.0.dist-info/RECORD
