Metadata-Version: 2.1
Name: crepex-pyutil
Version: 0.18.0
Summary: CrepeX python utilities
Author: Hyunwoo Shim
Author-email: hyunwoo.shim@crepe-x.com
Requires-Python: >=3.9,<4.0
Classifier: Programming Language :: Python :: 3
Classifier: Programming Language :: Python :: 3.9
Classifier: Programming Language :: Python :: 3.10
Classifier: Programming Language :: Python :: 3.11
Classifier: Programming Language :: Python :: 3.12
Requires-Dist: requests (>=2.27.0,<3.0.0)
